{
  "type": "minecraft:block",
  "pools": [
    {
      "rolls": 0,
      "bonus_rolls": 0,
      "entries": [
        {
          "type": "minecraft:alternatives",
          "children": [
            {
              "type": "minecraft:item",
              "name": "kamenridercraft:stone_blade",
              "conditions": [
                {
                  "condition": "minecraft:match_tool",
                  "predicate": {
                    "enchantments": [
                      {
                        "enchantment": "minecraft:silk_touch",
                        "levels": {
                          "min": 1
                        }
                      }
                    ]
                  }
                }
              ]
            }
          ]
        }
      ]
    },
    {
      "rolls": 1,
      "entries": [
        {
          "type": "minecraft:item",
          "weight": 7,
          "name": "kamenridercraft:bladecard",
          "functions": [
            {
              "function": "minecraft:apply_bonus",
              "enchantment": "minecraft:fortune",
              "formula": "minecraft:ore_drops"
            },
            {
              "function": "minecraft:explosion_decay"
            }
          ]
        },
        {
          "type": "minecraft:item",
          "weight": 4,
          "name": "kamenridercraft:change_beetle",
          "functions": [
            {
              "function": "minecraft:apply_bonus",
              "enchantment": "minecraft:fortune",
              "formula": "minecraft:ore_drops"
            },
            {
              "function": "minecraft:explosion_decay"
            }
          ]
        },
        {
          "type": "minecraft:item",
          "weight": 2,
          "name": "kamenridercraft:fusion_eagle",
          "functions": [
            {
              "function": "minecraft:apply_bonus",
              "enchantment": "minecraft:fortune",
              "formula": "minecraft:ore_drops"
            },
            {
              "function": "minecraft:explosion_decay"
            }
          ]
        },
        {
          "type": "minecraft:item",
          "weight": 2,
          "name": "kamenridercraft:absorb_capricorn",
          "functions": [
            {
              "function": "minecraft:apply_bonus",
              "enchantment": "minecraft:fortune",
              "formula": "minecraft:ore_drops"
            },
            {
              "function": "minecraft:explosion_decay"
            }
          ]
        },
        {
          "type": "minecraft:item",
          "weight": 1,
          "name": "kamenridercraft:evolution_caucasus",
          "functions": [
            {
              "function": "minecraft:apply_bonus",
              "enchantment": "minecraft:fortune",
              "formula": "minecraft:ore_drops"
            },
            {
              "function": "minecraft:explosion_decay"
            }
          ]
        },
        {
          "type": "minecraft:item",
          "weight": 4,
          "name": "kamenridercraft:change_stag",
          "functions": [
            {
              "function": "minecraft:apply_bonus",
              "enchantment": "minecraft:fortune",
              "formula": "minecraft:ore_drops"
            },
            {
              "function": "minecraft:explosion_decay"
            }
          ]
        },
        {
          "type": "minecraft:item",
          "weight": 2,
          "name": "kamenridercraft:fusion_peacock",
          "functions": [
            {
              "function": "minecraft:apply_bonus",
              "enchantment": "minecraft:fortune",
              "formula": "minecraft:ore_drops"
            },
            {
              "function": "minecraft:explosion_decay"
            }
          ]
        },
        {
          "type": "minecraft:item",
          "weight": 2,
          "name": "kamenridercraft:absorb_serpent",
          "functions": [
            {
              "function": "minecraft:apply_bonus",
              "enchantment": "minecraft:fortune",
              "formula": "minecraft:ore_drops"
            },
            {
              "function": "minecraft:explosion_decay"
            }
          ]
        },
        {
          "type": "minecraft:item",
          "weight": 1,
          "name": "kamenridercraft:evolution_giraffa",
          "functions": [
            {
              "function": "minecraft:apply_bonus",
              "enchantment": "minecraft:fortune",
              "formula": "minecraft:ore_drops"
            },
            {
              "function": "minecraft:explosion_decay"
            }
          ]
        },
        {
          "type": "minecraft:item",
          "weight": 3,
          "name": "kamenridercraft:change_mantis",
          "functions": [
            {
              "function": "minecraft:apply_bonus",
              "enchantment": "minecraft:fortune",
              "formula": "minecraft:ore_drops"
            },
            {
              "function": "minecraft:explosion_decay"
            }
          ]
        },
        {
          "type": "minecraft:item",
          "weight": 1,
          "name": "kamenridercraft:evolution_paradoxa",
          "functions": [
            {
              "function": "minecraft:apply_bonus",
              "enchantment": "minecraft:fortune",
              "formula": "minecraft:ore_drops"
            },
            {
              "function": "minecraft:explosion_decay"
            }
          ]
        },
        {
          "type": "minecraft:item",
          "weight": 3,
          "name": "kamenridercraft:change_spider",
          "functions": [
            {
              "function": "minecraft:apply_bonus",
              "enchantment": "minecraft:fortune",
              "formula": "minecraft:ore_drops"
            },
            {
              "function": "minecraft:explosion_decay"
            }
          ]
        },
        {
          "type": "minecraft:item",
          "weight": 2,
          "name": "kamenridercraft:fusion_elephant",
          "functions": [
            {
              "function": "minecraft:apply_bonus",
              "enchantment": "minecraft:fortune",
              "formula": "minecraft:ore_drops"
            },
            {
              "function": "minecraft:explosion_decay"
            }
          ]
        },
        {
          "type": "minecraft:item",
          "weight": 1,
          "name": "kamenridercraft:absorb_tiger",
          "functions": [
            {
              "function": "minecraft:apply_bonus",
              "enchantment": "minecraft:fortune",
              "formula": "minecraft:ore_drops"
            },
            {
              "function": "minecraft:explosion_decay"
            }
          ]
        },
        {
          "type": "minecraft:item",
          "weight": 1,
          "name": "kamenridercraft:evolution_tarantula",
          "functions": [
            {
              "function": "minecraft:apply_bonus",
              "enchantment": "minecraft:fortune",
              "formula": "minecraft:ore_drops"
            },
            {
              "function": "minecraft:explosion_decay"
            }
          ]
        },
        {
          "type": "minecraft:item",
          "weight": 1,
          "name": "kamenridercraft:change_kerberos_glaive",
          "functions": [
            {
              "function": "minecraft:apply_bonus",
              "enchantment": "minecraft:fortune",
              "formula": "minecraft:ore_drops"
            },
            {
              "function": "minecraft:explosion_decay"
            }
          ]
        },
        {
          "type": "minecraft:item",
          "weight": 3,
          "name": "kamenridercraft:change_kerberos_lance",
          "functions": [
            {
              "function": "minecraft:apply_bonus",
              "enchantment": "minecraft:fortune",
              "formula": "minecraft:ore_drops"
            },
            {
              "function": "minecraft:explosion_decay"
            }
          ]
        },
        {
          "type": "minecraft:item",
          "weight": 3,
          "name": "kamenridercraft:change_kerberos_larc",
          "functions": [
            {
              "function": "minecraft:apply_bonus",
              "enchantment": "minecraft:fortune",
              "formula": "minecraft:ore_drops"
            },
            {
              "function": "minecraft:explosion_decay"
            }
          ]
        }
      ]
    }
  ],
  "random_sequence": "kamenridercraft:stone_blade"
}