{
  "type": "minecraft:entity",
  "pools": [
    {
      "rolls": {
        "min": 0,
        "max": 1
      },
      "bonus_rolls": 0,
      "entries": [
        {
          "type": "minecraft:item",
          "weight": 10,
          "name": "kamenridercraft:kujaku_medal"
        },
        {
          "type": "minecraft:item",
          "weight": 10,
          "name": "kamenridercraft:condor_medal"
        },
        {
          "type": "minecraft:item",
          "weight": 5,
          "name": "kamenridercraft:taka_medal"
        }
      ]
    },
    {
      "rolls": 1,
      "entries": [
        {
          "type": "minecraft:item",
          "name": "kamenridercraft:taka_ankh_medal"
        }
      ]
    },
    {
      "rolls": 1,
      "entries": [
        {
          "type": "minecraft:item",
          "name": "kamenridercraft:greeed_blet_ankh"
        }
      ]
    },
    {
      "rolls": 1,
      "entries": [
        {
          "type": "minecraft:item",
          "name": "kamenridercraft:cellmedal",
          "functions": [
            {
              "function": "minecraft:set_count",
              "count": {
                "min": 3,
                "max": 6
              }
            }
          ]
        }
      ]
    }
  ]
}
